odoo/addons/project_odoo_version/README.rst
odoo/addons/project_odoo_version/__init__.py
odoo/addons/project_odoo_version/__manifest__.py
odoo/addons/project_odoo_version/data/data.xml
odoo/addons/project_odoo_version/i18n/ca_ES.po
odoo/addons/project_odoo_version/i18n/es.po
odoo/addons/project_odoo_version/models/__init__.py
odoo/addons/project_odoo_version/models/project_odoo_version.py
odoo/addons/project_odoo_version/models/project_project.py
odoo/addons/project_odoo_version/models/project_task.py
odoo/addons/project_odoo_version/readme/CONFIGURE.rst
odoo/addons/project_odoo_version/readme/CONTRIBUTORS.rst
odoo/addons/project_odoo_version/readme/DESCRIPTION.rst
odoo/addons/project_odoo_version/readme/USAGE.rst
odoo/addons/project_odoo_version/security/ir.model.access.csv
odoo/addons/project_odoo_version/static/description/icon.png
odoo/addons/project_odoo_version/static/description/index.html
odoo/addons/project_odoo_version/tests/__init__.py
odoo/addons/project_odoo_version/tests/test_project_odoo_version.py
odoo/addons/project_odoo_version/views/project_odoo_version_views.xml
odoo/addons/project_odoo_version/views/project_task_views.xml
odoo/addons/project_odoo_version/views/project_views.xml
odoo_addon_project_odoo_version-16.0.1.0.0.dist-info/METADATA
odoo_addon_project_odoo_version-16.0.1.0.0.dist-info/WHEEL
odoo_addon_project_odoo_version-16.0.1.0.0.dist-info/top_level.txt
odoo_addon_project_odoo_version-16.0.1.0.0.dist-info/RECORD
